{
  "openapi": "3.0.4",
  "info": {
    "title": "Shift Planner - API",
    "version": "1.0"
  },
  "paths": {
    "/api/Employee": {
      "get": {
        "tags": [
          "Employee"
        ],
        "responses": {
          "200": {
            "description": "OK",
            "content": {
              "text/plain": {
                "schema": {
                  "type": "array",
                  "items": {
                    "$ref": "#/components/schemas/Employee"
                  }
                }
              },
              "application/json": {
                "schema": {
                  "type": "array",
                  "items": {
                    "$ref": "#/components/schemas/Employee"
                  }
                }
              },
              "text/json": {
                "schema": {
                  "type": "array",
                  "items": {
                    "$ref": "#/components/schemas/Employee"
                  }
                }
              }
            }
          }
        }
      },
      "post": {
        "tags": [
          "Employee"
        ],
        "requestBody": {
          "content": {
            "application/json": {
              "schema": {
                "$ref": "#/components/schemas/Employee"
              }
            },
            "text/json": {
              "schema": {
                "$ref": "#/components/schemas/Employee"
              }
            },
            "application/*+json": {
              "schema": {
                "$ref": "#/components/schemas/Employee"
              }
            }
          }
        },
        "responses": {
          "200": {
            "description": "OK",
            "content": {
              "text/plain": {
                "schema": {
                  "$ref": "#/components/schemas/Employee"
                }
              },
              "application/json": {
                "schema": {
                  "$ref": "#/components/schemas/Employee"
                }
              },
              "text/json": {
                "schema": {
                  "$ref": "#/components/schemas/Employee"
                }
              }
            }
          }
        }
      }
    },
    "/api/Employee/{id}": {
      "get": {
        "tags": [
          "Employee"
        ],
        "parameters": [
          {
            "name": "id",
            "in": "path",
            "required": true,
            "schema": {
              "type": "integer",
              "format": "int32"
            }
          }
        ],
        "responses": {
          "200": {
            "description": "OK",
            "content": {
              "text/plain": {
                "schema": {
                  "$ref": "#/components/schemas/Employee"
                }
              },
              "application/json": {
                "schema": {
                  "$ref": "#/components/schemas/Employee"
                }
              },
              "text/json": {
                "schema": {
                  "$ref": "#/components/schemas/Employee"
                }
              }
            }
          }
        }
      },
      "put": {
        "tags": [
          "Employee"
        ],
        "parameters": [
          {
            "name": "id",
            "in": "path",
            "required": true,
            "schema": {
              "type": "integer",
              "format": "int32"
            }
          }
        ],
        "requestBody": {
          "content": {
            "application/json": {
              "schema": {
                "$ref": "#/components/schemas/Employee"
              }
            },
            "text/json": {
              "schema": {
                "$ref": "#/components/schemas/Employee"
              }
            },
            "application/*+json": {
              "schema": {
                "$ref": "#/components/schemas/Employee"
              }
            }
          }
        },
        "responses": {
          "200": {
            "description": "OK"
          }
        }
      },
      "delete": {
        "tags": [
          "Employee"
        ],
        "parameters": [
          {
            "name": "id",
            "in": "path",
            "required": true,
            "schema": {
              "type": "integer",
              "format": "int32"
            }
          }
        ],
        "responses": {
          "200": {
            "description": "OK"
          }
        }
      }
    },
    "/api/Employee/{id}/schedule": {
      "get": {
        "tags": [
          "Employee"
        ],
        "parameters": [
          {
            "name": "id",
            "in": "path",
            "required": true,
            "schema": {
              "type": "integer",
              "format": "int32"
            }
          }
        ],
        "responses": {
          "200": {
            "description": "OK",
            "content": {
              "text/plain": {
                "schema": {
                  "$ref": "#/components/schemas/Employee"
                }
              },
              "application/json": {
                "schema": {
                  "$ref": "#/components/schemas/Employee"
                }
              },
              "text/json": {
                "schema": {
                  "$ref": "#/components/schemas/Employee"
                }
              }
            }
          }
        }
      }
    },
    "/api/Shift": {
      "get": {
        "tags": [
          "Shift"
        ],
        "responses": {
          "200": {
            "description": "OK",
            "content": {
              "text/plain": {
                "schema": {
                  "type": "array",
                  "items": {
                    "$ref": "#/components/schemas/Shift"
                  }
                }
              },
              "application/json": {
                "schema": {
                  "type": "array",
                  "items": {
                    "$ref": "#/components/schemas/Shift"
                  }
                }
              },
              "text/json": {
                "schema": {
                  "type": "array",
                  "items": {
                    "$ref": "#/components/schemas/Shift"
                  }
                }
              }
            }
          }
        }
      },
      "post": {
        "tags": [
          "Shift"
        ],
        "requestBody": {
          "content": {
            "application/json": {
              "schema": {
                "$ref": "#/components/schemas/Shift"
              }
            },
            "text/json": {
              "schema": {
                "$ref": "#/components/schemas/Shift"
              }
            },
            "application/*+json": {
              "schema": {
                "$ref": "#/components/schemas/Shift"
              }
            }
          }
        },
        "responses": {
          "200": {
            "description": "OK",
            "content": {
              "text/plain": {
                "schema": {
                  "$ref": "#/components/schemas/Shift"
                }
              },
              "application/json": {
                "schema": {
                  "$ref": "#/components/schemas/Shift"
                }
              },
              "text/json": {
                "schema": {
                  "$ref": "#/components/schemas/Shift"
                }
              }
            }
          }
        }
      }
    },
    "/api/Shift/{id}": {
      "get": {
        "tags": [
          "Shift"
        ],
        "parameters": [
          {
            "name": "id",
            "in": "path",
            "required": true,
            "schema": {
              "type": "integer",
              "format": "int32"
            }
          }
        ],
        "responses": {
          "200": {
            "description": "OK",
            "content": {
              "text/plain": {
                "schema": {
                  "$ref": "#/components/schemas/Shift"
                }
              },
              "application/json": {
                "schema": {
                  "$ref": "#/components/schemas/Shift"
                }
              },
              "text/json": {
                "schema": {
                  "$ref": "#/components/schemas/Shift"
                }
              }
            }
          }
        }
      },
      "put": {
        "tags": [
          "Shift"
        ],
        "parameters": [
          {
            "name": "id",
            "in": "path",
            "required": true,
            "schema": {
              "type": "integer",
              "format": "int32"
            }
          }
        ],
        "requestBody": {
          "content": {
            "application/json": {
              "schema": {
                "$ref": "#/components/schemas/Shift"
              }
            },
            "text/json": {
              "schema": {
                "$ref": "#/components/schemas/Shift"
              }
            },
            "application/*+json": {
              "schema": {
                "$ref": "#/components/schemas/Shift"
              }
            }
          }
        },
        "responses": {
          "200": {
            "description": "OK"
          }
        }
      },
      "delete": {
        "tags": [
          "Shift"
        ],
        "parameters": [
          {
            "name": "id",
            "in": "path",
            "required": true,
            "schema": {
              "type": "integer",
              "format": "int32"
            }
          }
        ],
        "responses": {
          "200": {
            "description": "OK"
          }
        }
      }
    },
    "/api/Shift/{id}/employee": {
      "get": {
        "tags": [
          "Shift"
        ],
        "parameters": [
          {
            "name": "id",
            "in": "path",
            "required": true,
            "schema": {
              "type": "integer",
              "format": "int32"
            }
          }
        ],
        "responses": {
          "200": {
            "description": "OK",
            "content": {
              "text/plain": {
                "schema": {
                  "$ref": "#/components/schemas/Shift"
                }
              },
              "application/json": {
                "schema": {
                  "$ref": "#/components/schemas/Shift"
                }
              },
              "text/json": {
                "schema": {
                  "$ref": "#/components/schemas/Shift"
                }
              }
            }
          }
        }
      }
    }
  },
  "components": {
    "schemas": {
      "DayOfWeek": {
        "enum": [
          0,
          1,
          2,
          3,
          4,
          5,
          6
        ],
        "type": "integer",
        "format": "int32"
      },
      "Employee": {
        "required": [
          "employeeID",
          "name",
          "role"
        ],
        "type": "object",
        "properties": {
          "employeeID": {
            "type": "integer",
            "format": "int32"
          },
          "name": {
            "maxLength": 100,
            "minLength": 0,
            "type": "string"
          },
          "startDate": {
            "type": "string",
            "format": "date-time"
          },
          "weeklyHours": {
            "maximum": 60,
            "minimum": 1,
            "type": "integer",
            "format": "int32"
          },
          "role": {
            "$ref": "#/components/schemas/Role"
          },
          "shifts": {
            "type": "array",
            "items": {
              "$ref": "#/components/schemas/Shift"
            },
            "nullable": true
          }
        },
        "additionalProperties": false
      },
      "Role": {
        "enum": [
          0,
          1,
          2,
          3
        ],
        "type": "integer",
        "format": "int32"
      },
      "Shift": {
        "required": [
          "breakDuration",
          "employeeID"
        ],
        "type": "object",
        "properties": {
          "shiftID": {
            "type": "integer",
            "format": "int32"
          },
          "employeeID": {
            "type": "integer",
            "format": "int32"
          },
          "employee": {
            "$ref": "#/components/schemas/Employee"
          },
          "startTime": {
            "type": "string",
            "format": "date-time"
          },
          "endTime": {
            "type": "string",
            "format": "date-time"
          },
          "breakDuration": {
            "maximum": 180,
            "minimum": 0,
            "type": "integer",
            "format": "int32"
          },
          "day": {
            "$ref": "#/components/schemas/DayOfWeek"
          }
        },
        "additionalProperties": false
      }
    }
  },
  "tags": [
    {
      "name": "Employee"
    },
    {
      "name": "Shift"
    }
  ]
}